assignmenttest1/__init__.py
assignmenttest1/mainfile.py
assignmenttest1-0.0.2.dist-info/METADATA
assignmenttest1-0.0.2.dist-info/WHEEL
assignmenttest1-0.0.2.dist-info/top_level.txt
assignmenttest1-0.0.2.dist-info/RECORD
